riweather/__about__.py
riweather/__init__.py
riweather/cli.py
riweather/connection.py
riweather/parser.py
riweather/stations.py
riweather/utils.py
riweather/viz.py
riweather/db/__init__.py
riweather/db/actions.py
riweather/db/models.py
riweather/resources/metadata.db
riweather-1.0.2.dist-info/METADATA
riweather-1.0.2.dist-info/WHEEL
riweather-1.0.2.dist-info/entry_points.txt
riweather-1.0.2.dist-info/licenses/LICENSE
riweather-1.0.2.dist-info/RECORD
