Metadata-Version: 2.4
Name: riweather
Version: 1.0.2
Summary: Grab publicly available weather data
Author-email: John Ensley <jensley@resource-innovations.com>
License-Expression: Apache-2.0
License-File: LICENSE
Keywords: noaa,weather
Requires-Python: >=3.10
Requires-Dist: click>=8.1.3
Requires-Dist: pandas>=2.2
Requires-Dist: pydantic>=2.10.6
Requires-Dist: pyproj>=3.7.0
Requires-Dist: pyshp>=2.3.1
Requires-Dist: requests>=2.28.1
Requires-Dist: shapely>=2.0.0
Requires-Dist: sqlalchemy>=2.0.20
Provides-Extra: plots
Requires-Dist: folium>=0.14.0; extra == 'plots'
Requires-Dist: matplotlib>=3.6.2; extra == 'plots'
